waterdynamics/__init__.py
waterdynamics/waterdynamics.py
waterdynamics/tests/__init__.py
waterdynamics/tests/test_waterdynamics.py
waterdynamics-1.1.0.dist-info/AUTHORS.md
waterdynamics-1.1.0.dist-info/LICENSE
waterdynamics-1.1.0.dist-info/METADATA
waterdynamics-1.1.0.dist-info/WHEEL
waterdynamics-1.1.0.dist-info/top_level.txt
waterdynamics-1.1.0.dist-info/RECORD
